torch_ttt/__init__.py
torch_ttt/engine_registry.py
torch_ttt/loss_registry.py
torch_ttt/engine/__init__.py
torch_ttt/engine/actmad_engine.py
torch_ttt/engine/base_engine.py
torch_ttt/engine/deyo_engine.py
torch_ttt/engine/eata_engine.py
torch_ttt/engine/it3_engine.py
torch_ttt/engine/masked_ttt_engine.py
torch_ttt/engine/memo_engine.py
torch_ttt/engine/tent_engine.py
torch_ttt/engine/ttt_engine.py
torch_ttt/engine/ttt_pp_engine.py
torch_ttt/loss/__init__.py
torch_ttt/loss/base_loss.py
torch_ttt/loss/contrastive_loss.py
torch_ttt/loss/entropy_loss.py
torch_ttt/loss/mean_loss.py
torch_ttt/loss/ttt_loss.py
torch_ttt/loss/weights_magnitude_loss.py
torch_ttt/loss/zerot_loss.py
torch_ttt/utils/__init__.py
torch_ttt/utils/augmentations.py
torch_ttt/utils/math.py
torch_ttt-0.0.2.dist-info/licenses/LICENSE
torch_ttt-0.0.2.dist-info/METADATA
torch_ttt-0.0.2.dist-info/WHEEL
torch_ttt-0.0.2.dist-info/top_level.txt
torch_ttt-0.0.2.dist-info/RECORD
