Metadata-Version: 2.4
Name: torch-ttt
Version: 0.0.2
Summary: Test-Time Training / Adaptation engine collection for PyTorch.
Author-email: Nikita Durasov <yassnda@gmail.com>
License: MIT License
Project-URL: Homepage, https://torch-ttt.github.io
Project-URL: Documentation, https://torch-ttt.github.io
Project-URL: Repository, https://github.com/nikitadurasov/torch-ttt
Project-URL: Issues, https://github.com/nikitadurasov/torch-ttt/issues
Keywords: test-time training,test-time adaptation,domain adaptation,pytorch,deep learning,machine learning
Classifier: Development Status :: 3 - Alpha
Classifier: Intended Audience :: Developers
Classifier: Intended Audience :: Science/Research
Classifier: License :: OSI Approved :: MIT License
Classifier: Programming Language :: Python :: 3
Classifier: Programming Language :: Python :: 3.10
Classifier: Programming Language :: Python :: 3.11
Classifier: Programming Language :: Python :: 3.12
Classifier: Topic :: Scientific/Engineering :: Artificial Intelligence
Classifier: Topic :: Software Development :: Libraries :: Python Modules
Requires-Python: >=3.10
License-File: LICENSE
Provides-Extra: dev
Requires-Dist: pytest-cov; extra == "dev"
Provides-Extra: docs
Requires-Dist: sphinxawesome-theme==6.0.0b1; extra == "docs"
Requires-Dist: sphinx-gallery==0.18.0; extra == "docs"
Requires-Dist: sphinxcontrib-bibtex; extra == "docs"
Requires-Dist: sphinxcontrib-googleanalytics; extra == "docs"
Requires-Dist: matplotlib; extra == "docs"
Requires-Dist: tqdm; extra == "docs"
Provides-Extra: all
Requires-Dist: pytest-cov; extra == "all"
Requires-Dist: sphinxawesome-theme==6.0.0b1; extra == "all"
Requires-Dist: sphinx-gallery==0.18.0; extra == "all"
Requires-Dist: sphinxcontrib-bibtex; extra == "all"
Requires-Dist: sphinxcontrib-googleanalytics; extra == "all"
Requires-Dist: matplotlib; extra == "all"
Requires-Dist: tqdm; extra == "all"
Requires-Dist: einops; extra == "all"
Dynamic: license-file
